gumo/__init__.py
gumo/dev_server/__init__.py
gumo/dev_server/infrastrucutre/__init__.py
gumo/dev_server/presentation/__init__.py
gumo/dev_server/presentation/cli/__init__.py
gumo/dev_server/presentation/cli/template/admin_dashboard.html
gumo_dev_server-0.3.2.dist-info/LICENSE
gumo_dev_server-0.3.2.dist-info/METADATA
gumo_dev_server-0.3.2.dist-info/WHEEL
gumo_dev_server-0.3.2.dist-info/entry_points.txt
gumo_dev_server-0.3.2.dist-info/top_level.txt
gumo_dev_server-0.3.2.dist-info/RECORD
