Metadata-Version: 2.1
Name: gumo-dev-server
Version: 0.3.2
Summary: Gumo Dev Server Utilities
Home-page: https://github.com/gumo-py/gumo-dev-server
Author: Gumo Project Team
Author-email: gumo-py@googlegroups.com
License: UNKNOWN
Platform: UNKNOWN
Classifier: Programming Language :: Python :: 3
Classifier: License :: OSI Approved :: MIT License
Classifier: Operating System :: OS Independent
Requires-Dist: pyyaml (>=5.1)
Requires-Dist: injector (>=0.13.1)
Requires-Dist: gumo-core (>=0.1.3)
Requires-Dist: gumo-task-emulator (>=0.2.5,>=0.3.0)
Requires-Dist: datastore-viewer (>=0.3.1)
